requests_toolbelt/__init__.py
requests_toolbelt/_compat.py
requests_toolbelt/exceptions.py
requests_toolbelt/sessions.py
requests_toolbelt/streaming_iterator.py
requests_toolbelt/adapters/__init__.py
requests_toolbelt/adapters/appengine.py
requests_toolbelt/adapters/fingerprint.py
requests_toolbelt/adapters/host_header_ssl.py
requests_toolbelt/adapters/socket_options.py
requests_toolbelt/adapters/source.py
requests_toolbelt/adapters/ssl.py
requests_toolbelt/adapters/x509.py
requests_toolbelt/auth/__init__.py
requests_toolbelt/auth/_digest_auth_compat.py
requests_toolbelt/auth/guess.py
requests_toolbelt/auth/handler.py
requests_toolbelt/auth/http_proxy_digest.py
requests_toolbelt/cookies/__init__.py
requests_toolbelt/cookies/forgetful.py
requests_toolbelt/downloadutils/__init__.py
requests_toolbelt/downloadutils/stream.py
requests_toolbelt/downloadutils/tee.py
requests_toolbelt/multipart/__init__.py
requests_toolbelt/multipart/decoder.py
requests_toolbelt/multipart/encoder.py
requests_toolbelt/threaded/__init__.py
requests_toolbelt/threaded/pool.py
requests_toolbelt/threaded/thread.py
requests_toolbelt/utils/__init__.py
requests_toolbelt/utils/deprecated.py
requests_toolbelt/utils/dump.py
requests_toolbelt/utils/formdata.py
requests_toolbelt/utils/user_agent.py
requests_toolbelt-0.10.0.dist-info/AUTHORS.rst
requests_toolbelt-0.10.0.dist-info/LICENSE
requests_toolbelt-0.10.0.dist-info/METADATA
requests_toolbelt-0.10.0.dist-info/WHEEL
requests_toolbelt-0.10.0.dist-info/top_level.txt
requests_toolbelt-0.10.0.dist-info/RECORD
